{"children":[{"gravatar":"http:\/\/www.gravatar.com\/avatar\/8e9ce9bfb86bd1c7a10d78d3115d5e31?s=30&d=identicon&r=x","name":"aoeu","date":"","children":[{"gravatar":"http:\/\/www.gravatar.com\/avatar\/4fcc306fc7006127a903a58eea682452?s=30&d=identicon&r=x","name":"jobs","date":"2012-08-27 06:04:16","children":[]},{"gravatar":"http:\/\/www.gravatar.com\/avatar\/8caf4bab332505b3f9d7682dce8e2261?s=30&d=identicon&r=x","name":"hack","date":"2012-08-27 04:22:58","children":[]},{"gravatar":"http:\/\/www.gravatar.com\/avatar\/a0d227cc64f2f4e9bf132cb109446746?s=30&d=identicon&r=x","name":"last","date":"2012-08-27 06:42:40","children":[]},{"gravatar":"http:\/\/www.gravatar.com\/avatar\/90e4fa268fdd1f2aafcd40a77fe9aec2?s=30&d=identicon&r=x","name":"kill","date":"2012-08-27 06:00:34","children":[]},{"gravatar":"http:\/\/www.gravatar.com\/avatar\/87e0fba02edcba0f5901cb143221c1af?s=30&d=identicon&r=x","name":"USER","date":"2012-08-27 03:29:39","children":[]},{"gravatar":"http:\/\/www.gravatar.com\/avatar\/d465c798947ffee897e21141f62bb34a?s=30&d=identicon&r=x","name":"aoeuaoeu","date":"2012-08-27 04:20:04","children":[]},{"gravatar":"http:\/\/www.gravatar.com\/avatar\/39e2fbe3adb6e57a72236b273c19b8c0?s=30&d=identicon&r=x","name":"snth","date":"2012-08-27 05:19:13","children":[]},{"gravatar":"http:\/\/www.gravatar.com\/avatar\/a1956c1d727f1df00d977f6ce75b8c20?s=30&d=identicon&r=x","name":"mane","date":"2012-08-27 05:55:30","children":[]},{"gravatar":"http:\/\/www.gravatar.com\/avatar\/678849835e2a7703f8e01015f71a2bba?s=30&d=identicon&r=x","name":"somany","date":"2012-08-27 06:32:08","children":[]},{"gravatar":"http:\/\/www.gravatar.com\/avatar\/9c84f87eeaa4268545348421cced6f7d?s=30&d=identicon&r=x","name":"ueoa","date":"2012-08-27 05:13:41","children":[]}]}]}